RoboMax/__init__.py
RoboMax-9.1.dist-info/LICENSE
RoboMax-9.1.dist-info/METADATA
RoboMax-9.1.dist-info/WHEEL
RoboMax-9.1.dist-info/top_level.txt
RoboMax-9.1.dist-info/RECORD
